aiverify_test_engine/__init__.py
aiverify_test_engine/__main__.py
aiverify_test_engine/converters/data_converter.py
aiverify_test_engine/interfaces/__init__.py
aiverify_test_engine/interfaces/ialgorithm.py
aiverify_test_engine/interfaces/iconverter.py
aiverify_test_engine/interfaces/idata.py
aiverify_test_engine/interfaces/imodel.py
aiverify_test_engine/interfaces/ipipeline.py
aiverify_test_engine/interfaces/iplugin.py
aiverify_test_engine/interfaces/iserializer.py
aiverify_test_engine/interfaces/itestresult.py
aiverify_test_engine/io/__init__.py
aiverify_test_engine/io/delimiterdata/__init__.py
aiverify_test_engine/io/delimiterdata/delimiterdata.py
aiverify_test_engine/io/delimiterserializer/__init__.py
aiverify_test_engine/io/delimiterserializer/delimiterserializer.py
aiverify_test_engine/io/imagedata/__init__.py
aiverify_test_engine/io/imagedata/imagedata.py
aiverify_test_engine/io/imageserializer/__init__.py
aiverify_test_engine/io/imageserializer/imageserializer.py
aiverify_test_engine/io/joblibserializer/__init__.py
aiverify_test_engine/io/joblibserializer/joblibserializer.py
aiverify_test_engine/io/lightgbmmodel/__init__.py
aiverify_test_engine/io/lightgbmmodel/lightgbmmodel.py
aiverify_test_engine/io/openapiconnector/__init__.py
aiverify_test_engine/io/openapiconnector/openapiconnector.py
aiverify_test_engine/io/pandasdata/__init__.py
aiverify_test_engine/io/pandasdata/pandasdata.py
aiverify_test_engine/io/pickleserializer/__init__.py
aiverify_test_engine/io/pickleserializer/pickleserializer.py
aiverify_test_engine/io/pytorchmodel/__init__.py
aiverify_test_engine/io/pytorchmodel/pytorchmodel.py
aiverify_test_engine/io/pytorchpipeline/__init__.py
aiverify_test_engine/io/pytorchpipeline/pytorchpipeline.py
aiverify_test_engine/io/pytorchserializer/__init__.py
aiverify_test_engine/io/pytorchserializer/pytorchserializer.py
aiverify_test_engine/io/sklearnmodel/__init__.py
aiverify_test_engine/io/sklearnmodel/sklearnmodel.py
aiverify_test_engine-2.1.0.dist-info/METADATA
aiverify_test_engine-2.1.0.dist-info/WHEEL
aiverify_test_engine-2.1.0.dist-info/licenses/AUTHORS.rst
aiverify_test_engine-2.1.0.dist-info/licenses/LICENSE
aiverify_test_engine-2.1.0.dist-info/licenses/NOTICE.md
aiverify_test_engine-2.1.0.dist-info/RECORD
